vectordb/__init__.py
vectordb/admin.py
vectordb/apps.py
vectordb/checks.py
vectordb/embedding_functions.py
vectordb/manager.py
vectordb/models.py
vectordb/queryset.py
vectordb/serializers.py
vectordb/settings.py
vectordb/shortcuts.py
vectordb/signals.py
vectordb/sync_signals.py
vectordb/tasks.py
vectordb/urls.py
vectordb/utils.py
vectordb/validators.py
vectordb/views.py
vectordb/ann/__init__.py
vectordb/ann/abcz.py
vectordb/ann/indexes.py
vectordb/ann/singleton.py
vectordb/cohere/__init__.py
vectordb/cohere/embed.py
vectordb/cohere/tests/__init__.py
vectordb/cohere/tests/test_embed.py
vectordb/management/__init__.py
vectordb/management/commands/__init__.py
vectordb/management/commands/vectordb_reset.py
vectordb/management/commands/vectordb_sync.py
vectordb/migrations/0001_initial.py
vectordb/migrations/0002_vector_created_at_vector_updated_at_and_more.py
vectordb/migrations/__init__.py
vectordb/openai_embeddings/__init__.py
vectordb/openai_embeddings/prelease.py
vectordb/openai_embeddings/release_v1.py
vectordb/openai_embeddings/tests/__init__.py
vectordb/openai_embeddings/tests/test_openai_embeddings.py
vectordb/tests/__init__.py
vectordb/tests/apps.py
vectordb/tests/dummy_module.py
vectordb/tests/models.py
vectordb/tests/settings.py
vectordb/tests/test_api_endpoint.py
vectordb/tests/test_db_indexes.py
vectordb/tests/test_embedding_functions.py
vectordb/tests/test_settings.py
vectordb/tests/test_singleton_meta.py
vectordb/tests/test_utils.py
vectordb/tests/test_vectordb.py
django_vectordb-0.4.0.dist-info/LICENSE
django_vectordb-0.4.0.dist-info/METADATA
django_vectordb-0.4.0.dist-info/WHEEL
django_vectordb-0.4.0.dist-info/top_level.txt
django_vectordb-0.4.0.dist-info/RECORD
