Metadata-Version: 2.1
Name: django-vectordb
Version: 0.4.0
Summary: Add extremely fast vector search to django with support for filtering and auto-sync through signals. Scalable to a billion vectors.
Home-page: https://github.com/pkavumba/django-vectordb.git
Author: Pride Kavumba
Author-email: pkavumba@gmail.com
License: Apache License 2.0
Classifier: Environment :: Web Environment
Classifier: Intended Audience :: Developers
Classifier: License :: OSI Approved :: Apache Software License
Classifier: Operating System :: OS Independent
Classifier: Programming Language :: Python
Classifier: Programming Language :: Python :: 3
Classifier: Programming Language :: Python :: 3.7
Classifier: Programming Language :: Python :: 3.8
Classifier: Programming Language :: Python :: 3.9
Classifier: Programming Language :: Python :: 3.10
Classifier: Programming Language :: Python :: 3.11
Classifier: Programming Language :: Python :: 3.12
Classifier: Framework :: Django
Classifier: Framework :: Django :: 3
Classifier: Framework :: Django :: 3.2
Classifier: Framework :: Django :: 4
Classifier: Framework :: Django :: 4.0
Classifier: Framework :: Django :: 4.1
Classifier: Framework :: Django :: 4.2
Classifier: Framework :: Django :: 5.0
Classifier: Topic :: Internet :: WWW/HTTP
Classifier: Topic :: Internet :: WWW/HTTP :: Dynamic Content
Requires-Python: >=3.6
License-File: LICENSE
Requires-Dist: Django >=2.2
Requires-Dist: hnswlib >=0.7.0
Requires-Dist: numpy
Provides-Extra: dev
Requires-Dist: tox ; extra == 'dev'
Requires-Dist: django ; extra == 'dev'
Requires-Dist: pytest ; extra == 'dev'
Requires-Dist: pytest-django ; extra == 'dev'
Requires-Dist: sentence-transformers ; extra == 'dev'
Requires-Dist: djangorestframework ; extra == 'dev'
Requires-Dist: django-filter ; extra == 'dev'
Requires-Dist: mkdocs ; extra == 'dev'
Requires-Dist: django-stubs ; extra == 'dev'
Requires-Dist: pre-commit ; extra == 'dev'
Requires-Dist: mkdocs-material ; extra == 'dev'
Requires-Dist: ruff ; extra == 'dev'
Provides-Extra: standard
Requires-Dist: sentence-transformers ; extra == 'standard'
Requires-Dist: djangorestframework ; extra == 'standard'
Requires-Dist: django-filter ; extra == 'standard'
Provides-Extra: tests
Requires-Dist: pytest ; extra == 'tests'
Requires-Dist: pytest-django ; extra == 'tests'
Requires-Dist: sentence-transformers ; extra == 'tests'
Requires-Dist: djangorestframework ; extra == 'tests'
Requires-Dist: django-filter ; extra == 'tests'
